notion/__init__.py
notion/api/__init__.py
notion/api/client/__init__.py
notion/api/client/client.py
notion/api/client/endpoints.py
notion/components/__init__.py
notion/components/page.py
notion/components/blocks/__init__.py
notion/components/blocks/callout.py
notion/components/blocks/code.py
notion/components/blocks/heading.py
notion/components/blocks/paragraph.py
notion/properties/__init__.py
notion/properties/checkbox.py
notion/properties/custom.py
notion/properties/description.py
notion/properties/multiselect.py
notion/properties/select.py
notion/properties/text.py
notion/properties/title.py
secnex_notion_api-0.0.6.dist-info/licenses/LICENSE
secnex_notion_api-0.0.6.dist-info/METADATA
secnex_notion_api-0.0.6.dist-info/WHEEL
secnex_notion_api-0.0.6.dist-info/top_level.txt
secnex_notion_api-0.0.6.dist-info/RECORD
