Metadata-Version: 2.4
Name: secnex_notion_api
Version: 0.0.6
Summary: A package to interact with the Notion API
Author-email: Björn Benouarets <bjorn@secnex.io>
License-Expression: MIT
Project-URL: Homepage, https://github.com/secnex/notion-api
Project-URL: Issues, https://github.com/secnex/notion-api/issues
Classifier: Programming Language :: Python :: 3
Classifier: Operating System :: OS Independent
Requires-Python: >=3.9
License-File: LICENSE
Dynamic: license-file
